wa2rasa/__init__.py
wa2rasa/cli.py
wa2rasa/my_rasa_dir/nlu.yml
wa2rasa/wa2rasa.py
wa2rasa/wa_example/My-WA-Skill-dialog.json
wa2rasa-0.1.2.dist-info/entry_points.txt
wa2rasa-0.1.2.dist-info/WHEEL
wa2rasa-0.1.2.dist-info/METADATA
wa2rasa-0.1.2.dist-info/RECORD
