Metadata-Version: 2.1
Name: wa2rasa
Version: 0.1.2
Summary: Convert Watson Assistant skill object to rasa nlu.yml file.
Home-page: https://github.com/SClovesgtx/wa2rasa
License: MIT
Keywords: rasa,watson,nlu,convert,translate
Author: Cloves Paiva
Author-email: clovesgtx@gmail.com
Requires-Python: >=3.8,<4.0
Classifier: License :: OSI Approved :: MIT License
Classifier: Operating System :: OS Independent
Classifier: Programming Language :: Python :: 3
Classifier: Programming Language :: Python :: 3.10
Classifier: Programming Language :: Python :: 3.8
Classifier: Programming Language :: Python :: 3.9
Requires-Dist: PyYAML (>=6.0,<7.0)
Requires-Dist: rich (>=12.5.1,<13.0.0)
Requires-Dist: typer (>=0.6.1,<0.7.0)
Project-URL: Repository, https://github.com/SClovesgtx/wa2rasa
